bevfs/__init__.py
bevfs/bevfs.py
bevfs-1.0.2.dist-info/LICENSE
bevfs-1.0.2.dist-info/METADATA
bevfs-1.0.2.dist-info/WHEEL
bevfs-1.0.2.dist-info/top_level.txt
bevfs-1.0.2.dist-info/RECORD
