Metadata-Version: 2.1
Name: bevfs
Version: 1.0.2
Summary: A package for feature selection in high dimensional data.
Home-page: https://github.com/Bilal39/Bird-Eye-View/tree/main
Author: Mohammed Bilal Shakeel
Author-email: mohammedbilalshakeel@gmail.com
License: UNKNOWN
Platform: UNKNOWN
Classifier: License :: OSI Approved :: MIT License
Classifier: Programming Language :: Python :: 3
Classifier: Operating System :: OS Independent
Requires-Python: >=3.6
Requires-Dist: pandas >=1.3.0
Requires-Dist: numpy >=1.21.0
Requires-Dist: scikit-learn >=0.24.0
